cloudshell/__init__.py
cloudshell/email/__init__.py
cloudshell/email/constants.py
cloudshell/email/email_config.py
cloudshell/email/email_helpers.py
cloudshell/email/email_service.py
cloudshell/email/email_templates/default_error.htm
test/__init__.py
test/test_email_config.py
test/test_email_service.py
test/test_helpers.py
cloudshell_email-0.5.1.dist-info/METADATA
cloudshell_email-0.5.1.dist-info/WHEEL
cloudshell_email-0.5.1.dist-info/top_level.txt
cloudshell_email-0.5.1.dist-info/RECORD
