Metadata-Version: 2.1
Name: cloudshell-email
Version: 0.5.1
Summary: A package providing email capabilities for the default setup workflow for training use cases
Home-page: UNKNOWN
Author: Quali
Author-email: support@qualisystems.com
License: UNKNOWN
Keywords: sandbox cloud training cloudshell
Platform: UNKNOWN
Classifier: Development Status :: 4 - Beta
Classifier: Topic :: Software Development :: Libraries
Classifier: License :: OSI Approved :: Apache Software License
Requires-Dist: cloudshell-automation-api (>9.0.0)
